{"title": "Real-Time Hair Rendering With Deep Opacity Maps", "description": "The paper \"Deep Opacity Maps\" is available here: http://www.cemyuksel.com/research/deepopacity/ Unofficial implementation: http://prideout.net/blog/?p=69 Recommended for you: The Dunning-Kruger Effect - https://www.youtube.com/watch?v=4Y7RI... Are We Living In a Computer Simulation? - https://www.youtube.com/watch?v=ATN9o... Two Minute Papers Merch: US: http://twominutepapers.com/ EU/Worldwide: https://shop.spreadshirt.net/TwoMinutePapers/", "link": "https://www.youtube.com/watch?v=7x2UvvD48Fw", "tags": ["Recommender"], "kind": "Paper", "host": "youtube.com", "learn_score": 1, "explore_score": 1, "compete_score": 0, "engagement_score": 0.7195, "date_project": "2017-07-16 00:00:00", "date_scraped": "2021-02-01 00:00:00", "words": 37, "sentences": 3, "language_code": "en", "language": "english", "language_score": "0.9999971394193884", "tags_descriptive": ["Recommender"], "description_lemmatized": "paper deep opacity map available httpwwwcemyukselcomresearchdeepopacity unofficial implementation httpprideoutnetblogp69 recommended dunningkruger effect httpswwwyoutubecomwatchv4y7ri living computer simulation httpswwwyoutubecomwatchvatn9o two minute paper merch u httptwominutepaperscom euworldwide httpsshopspreadshirtnettwominutepapers", "runtime": 0.011}