{"title": "Light Transport on Specular Microstructure", "description": "The paper \"Position-Normal Distributions for Efficient Rendering of Specular Microstructure\" is available here: http://people.eecs.berkeley.edu/~ling... http://people.eecs.berkeley.edu/~lingqi/ Vienna Rendering course: https://users.cg.tuwien.ac.at/zsolnai... https://www.youtube.com/playlist?list...", "link": "https://www.youtube.com/watch?v=GNx8rgNcw5c", "tags": [], "kind": "Paper", "host": "youtube.com", "learn_score": 1, "explore_score": 1, "compete_score": 0, "engagement_score": 0.696, "date_project": "2017-10-01 00:00:00", "date_scraped": "2021-02-01 00:00:00", "words": 20, "sentences": 3, "language_code": "en", "language": "english", "language_score": "0.9999975964950121", "tags_descriptive": [], "description_lemmatized": "paper positionnormal distribution efficient rendering specular microstructure available httppeopleeecsberkeleyeduling httppeopleeecsberkeleyedulingqi vienna rendering course httpsuserscgtuwienacatzsolnai httpswwwyoutubecomplaylistlist", "runtime": 0.008}