{"title": "Digital Creatures Learn to Cooperate", "description": "The paper \"Discovery of complex behaviors through contact-invariant optimization\" is available here: http://homes.cs.washington.edu/~todor... http://homes.cs.washington.edu/~todor... Our earlier episode on optimization: https://www.youtube.com/watch?v=1ypV5... Our technical write-up on our video rendering pipeline changes is available here: https://www.patreon.com/posts/improve...", "link": "https://www.youtube.com/watch?v=LmYKfU5O_NA", "tags": [], "kind": "Paper", "host": "youtube.com", "learn_score": 1, "explore_score": 1, "compete_score": 0, "engagement_score": 0.7185, "date_project": "2017-02-16 00:00:00", "date_scraped": "2021-02-01 00:00:00", "words": 33, "sentences": 4, "language_code": "en", "language": "english", "language_score": "0.999994922582355", "tags_descriptive": [], "description_lemmatized": "paper discovery complex behavior contactinvariant optimization available httphomescswashingtonedutodor httphomescswashingtonedutodor earlier episode optimization httpswwwyoutubecomwatchv1ypv5 technical writeup video rendering pipeline change available httpswwwpatreoncompostsimprove", "runtime": 0.008}