{"title": "notebooks", "description": "Various notebooks and tutorials on subjects of interest.", "link": "https://github.com/jmschrei/notebooks", "category": "Education & Research", "category_score": 0, "subcategory": "Student", "subcategory_score": 0, "tags": ["CV", "Classification", "DL", "Linear Regression", "Logistic Regression", "NLP", "ReLu", "Recommender", "Regression", "Supervised Learning"], "kind": "Project", "ml_libs": ["keras", "mxnet", "sklearn"], "host": "github.com", "license": "", "language": "english", "date_project": "2020-06-09 19:30:36", "date_scraped": "2020-12-20 09:18:59", "words": 8, "sentences": 1, "runtime": 0.001, "description_category": "Education & Research", "description_category_score": 0.4817226827144623, "description_category_runtime": 2.038, "description_subcategory": "Student", "description_subcategory_score": 0.6437240242958069, "description_subcategory_runtime": 2.975, "runtime_cat": 5.014, "programming_language": "Jupyter Notebook", "ml_score": "0.8", "engagement_score": "0.418", "language_code": "en", "language_score": "0.9999957762094128", "learn_score": 1, "explore_score": 0, "compete_score": 0, "description_lemmatized": "various notebook tutorial subject interest", "tags_descriptive": ["Computer Vision (CV)", "Classification", "Deep Learning (DL)", "Linear Regression", "Logistic Regression", "Natural Language Processing (NLP)", "Rectified Linear Unit (ReLU)", "Recommender", "Regression", "Supervised Learning"]}