{"title": "appmode", "description": "A Jupyter extensions that turns notebooks into web applications.", "link": "https://github.com/oschuett/appmode", "category": "Emergency & Relief", "category_score": 0, "subcategory": "Student", "subcategory_score": 0, "tags": ["Classification", "RL"], "kind": "Project", "ml_libs": ["pattern"], "host": "github.com", "license": "MIT", "language": "english", "date_project": "2020-06-09 08:15:54", "date_scraped": "2020-12-19 22:22:40", "words": 9, "sentences": 1, "runtime": 0.0, "description_category": "Emergency & Relief", "description_category_score": 0.4104407727718353, "description_category_runtime": 2.363, "description_subcategory": "Student", "description_subcategory_score": 0.7840189933776855, "description_subcategory_runtime": 3.479, "runtime_cat": 5.842, "programming_language": "Python", "ml_score": "1.0", "engagement_score": "0.584", "language_code": "en", "language_score": "0.9999956447265659", "learn_score": 1, "explore_score": 0, "compete_score": 0, "description_lemmatized": "jupyter extension turn notebook web application", "tags_descriptive": ["Classification", "Reinforcement Learning (RL)"]}