{"title": "python in a notebook", "description": "Collection of Jupyter Notebooks about Python programming", "link": "https://github.com/leriomaggio/python-in-a-notebook", "category": "Utilities", "category_score": 0, "subcategory": "Preventative and Reactive", "subcategory_score": 0, "tags": ["DL", "RL", "Recommender"], "kind": "Project", "ml_libs": ["pattern"], "host": "github.com", "license": "MIT", "language": "english", "date_project": "2016-06-22 18:04:43", "date_scraped": "2020-12-19 22:54:51", "words": 7, "sentences": 1, "runtime": 0.001, "description_category": "Utilities", "description_category_score": 0.08874164521694183, "description_category_runtime": 2.186, "description_subcategory": "Preventative and Reactive", "description_subcategory_score": 0.4535495638847351, "description_subcategory_runtime": 3.311, "runtime_cat": 5.497, "programming_language": "Jupyter Notebook", "ml_score": "0.8", "engagement_score": "0.512", "language_code": "en", "language_score": "0.9999961134797731", "learn_score": 1, "explore_score": 0, "compete_score": 0, "description_lemmatized": "collection jupyter notebook python programming", "tags_descriptive": ["Deep Learning (DL)", "Reinforcement Learning (RL)", "Recommender"]}