{"title": "RoamesNotebooks", "description": "Public Jupyter notebooks from Fugro Roames", "link": "https://github.com/FugroRoames/RoamesNotebooks", "category": "Justice, Law and Regulations", "category_score": 0, "subcategory": "Preventative and Reactive", "subcategory_score": 0, "tags": ["Classification", "DL", "Recommender"], "kind": "Project", "ml_libs": ["pattern", "tensorflow"], "host": "github.com", "license": "", "language": "english", "date_project": "2019-03-07 00:15:24", "date_scraped": "2020-12-19 23:57:06", "words": 6, "sentences": 1, "runtime": 0.001, "description_category": "Justice, Law and Regulations", "description_category_score": 0.2166384905576706, "description_category_runtime": 2.201, "description_subcategory": "Preventative and Reactive", "description_subcategory_score": 0.4297318458557129, "description_subcategory_runtime": 3.264, "runtime_cat": 5.466, "programming_language": "Jupyter Notebook", "ml_score": "0.8", "engagement_score": "0.39", "language_code": "en", "language_score": "0.9999954731047981", "learn_score": 1, "explore_score": 0, "compete_score": 0, "description_lemmatized": "public jupyter notebook fugro roames", "tags_descriptive": ["Classification", "Deep Learning (DL)", "Recommender"]}