{"title": "Gene Kogan, Jeff Snyder", "description": "Finger pressure sensors, a breath pressure and embouchure sensor on the mouthpiece mapped with an ANN to generate sound via a microcontroller", "link": "https://mlart.co/item/finger-pressure-sensors_-a-breath-pressure-and-embouchure-sensor-on-the-mouthpiece-mapped-with-an-ann-to-generate-sound-via-a-microcontroller", "category": "Miscellaneous", "category_score": 1, "subcategory": "Art", "subcategory_score": 1, "tags": ["Music", "Instrument", "ANN"], "kind": "Showcase", "host": "mlart.co", "date_project": "2014-01-01 00:00:00", "date_scraped": "2020-12-02 01:10:18", "words": 22, "sentences": 1, "runtime": 0.001, "language_code": "en", "language": "english", "language_score": "0.9999971747214571", "learn_score": 0, "explore_score": 1, "compete_score": 0, "description_lemmatized": "finger pressure sensor breath pressure embouchure sensor mouthpiece mapped ann generate sound via microcontroller", "tags_descriptive": ["Music", "Instrument", "Artificial Neural Network (ANN)"]}