{"title": "Lisha Li, Vladimir Glazachev, Dzmitry Pletnikau, Eric Liu", "description": "Automatically animate digital humans or your digital double with just text or speech", "link": "https://mlart.co/item/automatically-animate-digital-humans-or-your-digital-double-with-just-text-or-speech", "category": "Miscellaneous", "category_score": 1, "subcategory": "Art", "subcategory_score": 1, "tags": ["Character Animation", "Digital Doubles", "Virtual Personas", "Video", "Text to Animation"], "kind": "Showcase", "host": "mlart.co", "date_project": "2020-10-01 00:00:00", "date_scraped": "2020-12-02 00:13:16", "words": 13, "sentences": 1, "runtime": 0.001, "language_code": "en", "language": "english", "language_score": "0.9999967786651474", "learn_score": 0, "explore_score": 1, "compete_score": 0, "description_lemmatized": "automatically animate digital human digital double text speech", "tags_descriptive": ["Character Animation", "Digital Doubles", "Virtual Personas", "Video", "Text to Animation"]}