{"title": "Dani Joy", "description": "Produce large scale Style Transfer-like artworks, print, and paint over", "link": "https://mlart.co/item/produce-large-scale-style-transfer-like-artworks_-print_-and-paint-over", "category": "Miscellaneous", "category_score": 1, "subcategory": "Art", "subcategory_score": 1, "tags": ["Glitch", "Art", "Painting", "Style Transfer"], "kind": "Showcase", "host": "mlart.co", "date_project": "2018-01-01 00:00:00", "date_scraped": "2020-12-02 00:51:19", "words": 10, "sentences": 1, "runtime": 0.01, "language_code": "en", "language": "english", "language_score": "0.999995371756403", "learn_score": 0, "explore_score": 1, "compete_score": 0, "description_lemmatized": "produce large scale style transferlike artwork print paint", "tags_descriptive": ["Glitch", "Art", "Painting", "Style Transfer"]}