{"title": "Obvious", "description": "GAN trained on masks, and make the masks according to the GAN-generated images", "link": "https://mlart.co/item/gan-trained-on-masks_-and-make-the-masks-according-to-the-gan-generated-images", "category": "Miscellaneous", "category_score": 1, "subcategory": "Art", "subcategory_score": 1, "tags": ["Art", "Culture", "Mask", "GAN"], "kind": "Showcase", "host": "mlart.co", "date_project": "2020-05-01 00:00:00", "date_scraped": "2020-12-02 00:23:44", "words": 13, "sentences": 1, "runtime": 0.001, "language_code": "en", "language": "english", "language_score": "0.9999964979840692", "learn_score": 0, "explore_score": 1, "compete_score": 0, "description_lemmatized": "gan trained mask make mask according gangenerated image", "tags_descriptive": ["Art", "Culture", "Mask", "Generative Adversarial Networks (GAN)"]}