{"title": "Cervix Image Segmentation", "description": "Hi everyone, this kernel is about applying different segmentation methods to the images of the cervixMethods used:  a channel saturaion Watershed Edge detection K-means  References can be found at the beginning of each method", "link": "https://www.kaggle.com/zahaviguy/cervix-image-segmentation", "tags": [], "kind": ["Project", "(Notebook)"], "ml_libs": ["sklearn", "opencv-python"], "host": "kaggle.com", "license": "Apache-2.0", "language": "english", "date_project": "2017-05-09 13:24:58", "date_scraped": "2020-12-13 11:58:48", "words": 36, "sentences": 1, "runtime": 0.002, "description_category": "Healthcare", "description_category_score": 0.5410588383674622, "description_category_runtime": 4.664, "description_subcategory": "Tools", "description_subcategory_score": 0.288431316614151, "description_subcategory_runtime": 6.684, "category": "Healthcare", "category_score": 0.5410588383674622, "subcategory": "Tools", "subcategory_score": 0.288431316614151, "runtime_cat": 11.348, "programming_language": "Jupyter Notebook", "ml_score": "1.0", "engagement_score": "0.681", "language_code": "en", "language_score": "0.9999963775910868", "learn_score": 1, "explore_score": 0, "compete_score": 0, "description_lemmatized": "hi everyone kernel applying different segmentation method image cervixmethods used channel saturaion watershed edge detection kmeans reference found beginning method", "tags_descriptive": []}