{"title": "Herbarium - Consolidating the Details", "description": "PeekThis notebook is here to just unify the dataset into one. I will perform further analysis and the Deep Learning algorithm in a future kernel. If you like this kernel, or forked this version, please upvote. First step, we peek at the data paths:", "link": "https://www.kaggle.com/seraphwedd18/herbarium-consolidating-the-details", "tags": [], "kind": ["Project", "(Notebook)"], "ml_libs": ["sklearn", "keras", "tensorflow"], "host": "kaggle.com", "license": "Apache-2.0", "language": "english", "date_project": "2020-03-17 02:39:09", "date_scraped": "2020-12-12 20:41:48", "words": 44, "sentences": 4, "runtime": 0.0, "description_category": "Real Estate, Rental & Leasing", "description_category_score": 0.4160785675048828, "description_category_runtime": 5.127, "description_subcategory": "Rental & Leasing", "description_subcategory_score": 0.4683424234390259, "description_subcategory_runtime": 7.847, "category": "Real Estate, Rental & Leasing", "category_score": 0.4160785675048828, "subcategory": "Rental & Leasing", "subcategory_score": 0.4683424234390259, "runtime_cat": 12.975, "programming_language": "Jupyter Notebook", "ml_score": "1.0", "engagement_score": "0.719", "language_code": "en", "language_score": "0.9999965450597831", "learn_score": 1, "explore_score": 0, "compete_score": 0, "description_lemmatized": "peekthis notebook unify dataset one perform analysis deep learning algorithm future kernel like kernel forked version please upvote first step peek data path", "tags_descriptive": []}