{"title": "Outbrain EDA", "description": "Use this one simple trick to get to the top of the leaderboard - Grandmasters hate him!Here's quite a high-level EDA - since the data is so huge, we want to get a better understanding of what we actually have. If this EDA helps you, make sure to leave an upvote to motivate me to make more! :) First off: What files do we have?", "link": "https://www.kaggle.com/anokas/outbrain-eda", "tags": ["Exploratory Data Analysis"], "kind": ["Project", "(Notebook)"], "ml_libs": [], "host": "kaggle.com", "license": "Apache-2.0", "language": "english", "date_project": "2016-10-09 21:48:58", "date_scraped": "2020-12-13 15:00:19", "words": 65, "sentences": 2, "runtime": 0.0, "description_category": "Utilities", "description_category_score": 0.14858414232730865, "description_category_runtime": 6.733, "description_subcategory": "General", "description_subcategory_score": 0.22242189943790436, "description_subcategory_runtime": 10.227, "category": "Utilities", "category_score": 0.14858414232730865, "subcategory": "General", "subcategory_score": 0.22242189943790436, "runtime_cat": 16.961, "programming_language": "Jupyter Notebook", "ml_score": "0.5", "engagement_score": "0.787", "language_code": "en", "language_score": "0.9999973595087464", "learn_score": 1, "explore_score": 0, "compete_score": 0, "description_lemmatized": "use one simple trick get top leaderboard grandmaster hate himheres quite highlevel eda since data huge want get better understanding actually eda help make sure leave upvote motivate make first file", "tags_descriptive": ["Exploratory Data Analysis"]}