{"title": "Facial Recognition Competition Using FastAi", "description": "Using the Facial Recognition Challenge dataset with fastaiThis is my take on lesson's one and two of the fastai course. I decided to use this library and see how well it will work out of the box on the 2013 facial recognition challenge.", "link": "https://www.kaggle.com/muhammadumerbhutta/facial-recognition-competition-using-fastai", "tags": [], "kind": ["Project", "(Notebook)"], "ml_libs": ["pytorch"], "host": "kaggle.com", "license": "Apache-2.0", "language": "english", "date_project": "2020-11-11 09:51:28", "date_scraped": "2020-12-12 17:52:11", "words": 43, "sentences": 2, "runtime": 0.001, "description_category": "Healthcare", "description_category_score": 0.029806040227413177, "description_category_runtime": 4.747, "description_subcategory": "Machine Learning", "description_subcategory_score": 0.6479243040084839, "description_subcategory_runtime": 7.23, "category": "Healthcare", "category_score": 0.029806040227413177, "subcategory": "Machine Learning", "subcategory_score": 0.6479243040084839, "runtime_cat": 11.977, "programming_language": "Jupyter Notebook", "ml_score": "1.0", "engagement_score": "0.477", "language_code": "en", "language_score": "0.9999969934802985", "learn_score": 1, "explore_score": 0, "compete_score": 0, "description_lemmatized": "using facial recognition challenge dataset fastaithis take lesson one two fastai course decided use library see well work box 2013 facial recognition challenge", "tags_descriptive": []}