{"title": "Blue Book for Bulldozer - Kaggle Competition", "description": "Blue Book for Bulldozer - Kaggle Competition", "link": "https://www.kaggle.com/sureshsubramaniam/blue-book-for-bulldozer-kaggle-competition", "tags": [], "kind": ["Project", "(Notebook)"], "ml_libs": ["sklearn"], "host": "kaggle.com", "license": "Apache-2.0", "language": "english", "date_project": "2018-09-11 07:09:59", "date_scraped": "2020-12-12 17:19:45", "words": 7, "sentences": 1, "runtime": 0.0, "description_category": "Government and Public Works", "description_category_score": 0.00360734760761261, "description_category_runtime": 2.278, "description_subcategory": "Preventative and Reactive", "description_subcategory_score": 0.4482010304927826, "description_subcategory_runtime": 3.252, "category": "Government and Public Works", "category_score": 0.00360734760761261, "subcategory": "Preventative and Reactive", "subcategory_score": 0.4482010304927826, "runtime_cat": 5.53, "programming_language": "Jupyter Notebook", "ml_score": "1.0", "engagement_score": "0.69", "language_code": "en", "language_score": "0.9999958837919364", "learn_score": 1, "explore_score": 0, "compete_score": 0, "description_lemmatized": "blue book bulldozer kaggle competition", "tags_descriptive": []}