{"title": "Ion Switching - AdvFE, LGB, Wavenet, ConfMatrix", "description": "University of Liverpool - Ion Switching", "link": "https://www.kaggle.com/vbmokin/ion-switching-advfe-lgb-wavenet-confmatrix", "tags": ["Classification", "Feature Engineering"], "kind": ["Project", "(Notebook)"], "ml_libs": ["keras", "xgboost", "tensorflow", "lightgbm", "sklearn"], "host": "kaggle.com", "license": "Apache-2.0", "language": "english", "date_project": "2020-08-11 00:05:04", "date_scraped": "2020-12-13 13:17:30", "words": 6, "sentences": 1, "runtime": 0.0, "description_category": "Physics", "description_category_score": 0.5111175179481506, "description_category_runtime": 1.912, "description_subcategory": "Preventative and Reactive", "description_subcategory_score": 0.8574564456939697, "description_subcategory_runtime": 2.673, "category": "Physics", "category_score": 0.5111175179481506, "subcategory": "Preventative and Reactive", "subcategory_score": 0.8574564456939697, "runtime_cat": 4.587, "programming_language": "Jupyter Notebook", "ml_score": "1.0", "engagement_score": "0.764", "language_code": "en", "language_score": "0.9999979649769346", "learn_score": 1, "explore_score": 0, "compete_score": 0, "description_lemmatized": "university liverpool ion switching", "tags_descriptive": ["Classification", "Feature Engineering"]}