{"title": "Cellular Automata as a Language for Reasoning ", "description": "How to solve this task with cellular automata ?", "link": "https://www.kaggle.com/arsenynerinovsky/cellular-automata-as-a-language-for-reasoning", "tags": [], "kind": ["Project", "(Notebook)"], "ml_libs": ["pattern"], "host": "kaggle.com", "license": "Apache-2.0", "language": "english", "date_project": "2020-02-19 08:54:27", "date_scraped": "2020-12-12 16:09:11", "words": 9, "sentences": 1, "runtime": 0.001, "description_category": "Biotechnological & Life Sciences", "description_category_score": 0.529933512210846, "description_category_runtime": 2.154, "description_subcategory": "Tools", "description_subcategory_score": 0.6365033984184265, "description_subcategory_runtime": 3.122, "category": "Biotechnological & Life Sciences", "category_score": 0.529933512210846, "subcategory": "Tools", "subcategory_score": 0.6365033984184265, "runtime_cat": 5.276, "programming_language": "Jupyter Notebook", "ml_score": "1.0", "engagement_score": "0.782", "language_code": "en", "language_score": "0.9999966399782908", "learn_score": 1, "explore_score": 0, "compete_score": 0, "description_lemmatized": "solve task cellular automaton", "tags_descriptive": []}