{"title": "Dimensionality reduction (PCA, tSNE)", "description": "Simply loading the files without any transformation. If you wish to manipulate the data in any way, it should be done here before doing dimensionality reduction in subsequent steps.", "link": "https://www.kaggle.com/tilii7/dimensionality-reduction-pca-tsne", "tags": ["Dimensionality Reduction"], "kind": ["Project", "(Notebook)"], "ml_libs": ["sklearn"], "host": "kaggle.com", "license": "Apache-2.0", "language": "english", "date_project": "2017-10-19 19:51:44", "date_scraped": "2020-12-13 15:44:39", "words": 29, "sentences": 2, "runtime": 0.001, "description_category": "Utilities", "description_category_score": 0.39195361733436584, "description_category_runtime": 3.967, "description_subcategory": "Preventative and Reactive", "description_subcategory_score": 0.7045278549194336, "description_subcategory_runtime": 5.397, "category": "Utilities", "category_score": 0.39195361733436584, "subcategory": "Preventative and Reactive", "subcategory_score": 0.7045278549194336, "runtime_cat": 9.364, "programming_language": "Jupyter Notebook", "ml_score": "1.0", "engagement_score": "0.776", "language_code": "en", "language_score": "0.9999945457144227", "learn_score": 1, "explore_score": 0, "compete_score": 0, "description_lemmatized": "simply loading file without transformation wish manipulate data way done dimensionality reduction subsequent step", "tags_descriptive": ["Dimensionality Reduction"]}