{"title": "Yelp Data Analysis", "description": "Data Analysis In this kernel we try to do some simple insights into the training data on categorization of the resutaurant classification. I padded the labels to 9 categories and transformed them into individual columns in the dataframe with a value of N, if that category is not present in the input label and Y if that category is peresent in the lable. This rearrangement helps us to answer various questions:  How many restaurants serve lunch and dinner How many restaurants serve dinner with alcohol in the outdoors and are kid friendly How mant restaurants serve dinner only and need reservations", "link": "https://www.kaggle.com/sgovindu/yelp-data-analysis", "tags": [], "kind": ["Project", "(Notebook)"], "ml_libs": [], "host": "kaggle.com", "license": "Apache-2.0", "language": "english", "date_project": "2018-09-01 12:34:29", "date_scraped": "2020-12-13 18:36:56", "words": 102, "sentences": 3, "runtime": 0.002, "description_category": "Accommodation & Food", "description_category_score": 0.83652663230896, "description_category_runtime": 8.747, "description_subcategory": "Restaurant", "description_subcategory_score": 0.6507185697555542, "description_subcategory_runtime": 13.392, "category": "Accommodation & Food", "category_score": 0.83652663230896, "subcategory": "Restaurant", "subcategory_score": 0.6507185697555542, "runtime_cat": 22.14, "programming_language": "Jupyter Notebook", "ml_score": "0.5", "engagement_score": "0.602", "language_code": "en", "language_score": "0.9999947396645149", "learn_score": 1, "explore_score": 0, "compete_score": 0, "description_lemmatized": "data analysis kernel try simple insight training data categorization resutaurant classification padded label 9 category transformed individual column dataframe value n category present input label category peresent lable rearrangement help u answer various question many restaurant serve lunch dinner many restaurant serve dinner alcohol outdoors kid friendly mant restaurant serve dinner need reservation", "tags_descriptive": []}