{"title": "PetFinder.my: detailed EDA and XGBoost baseline", "description": "Table of contents Introduction 1. Loading libraries and preparing the data 2. Data exploration 2.1 Dogs versus Cats, Breed, and Maturity Size 2.2 Age 2.3 Gender and Groups 2.4 The influence of the Fee 2.5 Health and medical status 2.6 Regional differences 2.7 Text mining the Description 2.8 Pets with a name versus pets without name   3. Baseline XGBoost model", "link": "https://www.kaggle.com/erikbruin/petfinder-my-detailed-eda-and-xgboost-baseline", "tags": ["Exploratory Data Analysis"], "kind": ["Project", "(Notebook)"], "ml_libs": ["xgboost"], "host": "kaggle.com", "license": "Apache-2.0", "language": "english", "date_project": "2019-02-03 08:23:47", "date_scraped": "2020-12-13 15:07:40", "words": 62, "sentences": 4, "runtime": 0.0, "description_category": "Healthcare", "description_category_score": 0.23229190707206726, "description_category_runtime": 7.163, "description_subcategory": "Textual Analysis", "description_subcategory_score": 0.49910998344421387, "description_subcategory_runtime": 10.858, "category": "Healthcare", "category_score": 0.23229190707206726, "subcategory": "Textual Analysis", "subcategory_score": 0.49910998344421387, "runtime_cat": 18.02, "programming_language": "R notebook", "ml_score": "1.0", "engagement_score": "0.753", "language_code": "en", "language_score": "0.9999984885390945", "learn_score": 1, "explore_score": 0, "compete_score": 0, "description_lemmatized": "table content introduction 1 loading library preparing data 2 data exploration 21 dog versus cat breed maturity size 22 age 23 gender group 24 influence fee 25 health medical status 26 regional difference 27 text mining description 28 pet name versus pet without name 3 baseline xgboost model", "tags_descriptive": ["Exploratory Data Analysis"]}