{"title": "NFL simple model using lightGBM", "description": "IntroductionI will introduce a simple method using lightGBM as a starter.", "link": "https://www.kaggle.com/hukuda222/nfl-simple-model-using-lightgbm", "tags": [], "kind": ["Project", "(Notebook)"], "ml_libs": ["sklearn", "lightgbm"], "host": "kaggle.com", "license": "Apache-2.0", "language": "english", "date_project": "2019-10-14 05:12:43", "date_scraped": "2020-12-13 14:21:44", "words": 11, "sentences": 1, "runtime": 0.002, "description_category": "Biotechnological & Life Sciences", "description_category_score": 0.1736992448568344, "description_category_runtime": 2.558, "description_subcategory": "Student", "description_subcategory_score": 0.2954542934894562, "description_subcategory_runtime": 3.799, "category": "Biotechnological & Life Sciences", "category_score": 0.1736992448568344, "subcategory": "Student", "subcategory_score": 0.2954542934894562, "runtime_cat": 6.357, "programming_language": "Jupyter Notebook", "ml_score": "1.0", "engagement_score": "0.756", "language_code": "en", "language_score": "0.99999701725707", "learn_score": 1, "explore_score": 0, "compete_score": 0, "description_lemmatized": "introductioni introduce simple method using lightgbm starter", "tags_descriptive": []}