{"title": "RL", "description": "generating compounds predicted to be active against a biological target.", "link": "https://github.com/MarcusOlivecrona/REINVENT", "category": "Biotechnological & Life Sciences", "category_score": 1, "subcategory": "Chemoinformatics and drug discovery", "subcategory_score": 1, "tags": ["Classification", "GRU", "RL", "RNN"], "kind": "Project", "ml_libs": ["sklearn", "vocabulary"], "host": "github.com", "license": "MIT", "language": "english", "date_project": "2019-10-15 12:32:41", "date_scraped": "2020-10-30 23:52:46", "words": 10, "sentences": 1, "runtime": 0.0, "programming_language": "Python", "ml_score": "1.0", "engagement_score": "0.534", "language_code": "en", "language_score": "0.9999956800507641", "learn_score": 1, "explore_score": 0, "compete_score": 0.25, "description_lemmatized": "generating compound predicted active biological target", "tags_descriptive": ["Classification", "Gated Recurrent Unit (GRU)", "Reinforcement Learning (RL)", "Recurrent Neural Network (RNN)"]}