{"title": "NLP Finance Papers", "description": "Curating quantitative finance papers using machine learning.", "link": "https://github.com/chen-bowen/Research_Documents_Curation_with_NLP", "category": "Finance", "category_score": 1, "subcategory": "Trading & Investment", "subcategory_score": 1, "tags": ["CNN", "ReLu"], "kind": "Project", "ml_libs": ["gensim", "keras", "nltk", "vocabulary"], "host": "github.com", "license": "", "language": "english", "date_project": "2018-12-24 23:27:56", "date_scraped": "2020-10-31 00:37:03", "words": 7, "sentences": 1, "runtime": 0.005, "programming_language": "Jupyter Notebook", "ml_score": "1.0", "engagement_score": "0.292", "language_code": "en", "language_score": "0.9999966478033102", "learn_score": 1, "explore_score": 0, "compete_score": 0.25, "description_lemmatized": "curating quantitative finance paper using machine learning", "tags_descriptive": ["Convolutional Neural Network (CNN)", "Rectified Linear Unit (ReLU)"]}