{"title": "Loan Acceptance", "description": "Classification and time-series analysis for loan acceptance.", "link": "https://github.com/Paresh3189/Bankruptcy-Prediction-Growth-Modelling", "category": "Banking & Insurance", "category_score": 1, "subcategory": "Consumer Financial", "subcategory_score": 1, "tags": ["Classification", "Decision Tree", "Random Forest", "Regression"], "kind": "Project", "ml_libs": ["sklearn", "statsmodels"], "host": "github.com", "license": "", "language": "english", "date_project": "2018-10-21 15:21:16", "date_scraped": "2020-10-30 23:41:35", "words": 7, "sentences": 1, "runtime": 0.001, "programming_language": "Jupyter Notebook", "ml_score": "1.0", "engagement_score": "0.268", "language_code": "en", "language_score": "0.9999958683969526", "learn_score": 1, "explore_score": 0, "compete_score": 0.25, "description_lemmatized": "classification timeseries analysis loan acceptance", "tags_descriptive": ["Classification", "Decision Tree", "Random Forest", "Regression"]}