{"title": "Quality Control", "description": "Quality control for banking using LDA", "link": "https://github.com/mick-zhang/Quality-Control-for-Banking-using-LDA-and-LDA-Mallet", "category": "Banking & Insurance", "category_score": 1, "subcategory": "Insurance and Risk", "subcategory_score": 1, "tags": ["Supervised Learning", "Unsupervised Learning"], "kind": "Project", "ml_libs": ["gensim", "nltk", "spacy"], "host": "github.com", "license": "", "language": "english", "date_project": "2019-06-15 20:12:30", "date_scraped": "2020-10-30 23:43:52", "words": 6, "sentences": 1, "runtime": 0.0, "programming_language": "Jupyter Notebook", "ml_score": "1.0", "engagement_score": "0.099", "language_code": "en", "language_score": "0.99999773282432", "learn_score": 1, "explore_score": 0, "compete_score": 0.25, "description_lemmatized": "quality control banking using lda", "tags_descriptive": ["Supervised Learning", "Unsupervised Learning"]}