{"title": "CFPB", "description": "Consumer Finances Protection Bureau complaints analysis.", "link": "https://github.com/MAydogdu/ConsumerFinancialProtectionBureau/", "category": "Government and Public Works", "category_score": 1, "subcategory": "Social Policies", "subcategory_score": 1, "tags": ["Classification", "Sentiment Analysis"], "kind": "Project", "ml_libs": ["nltk"], "host": "github.com", "license": "", "language": "english", "date_project": "2017-09-28 19:31:58", "date_scraped": "2020-10-31 00:49:23", "words": 6, "sentences": 1, "runtime": 0.0, "programming_language": "Jupyter Notebook", "ml_score": "0.8", "engagement_score": "0.0", "language_code": "en", "language_score": "0.571428122953842", "learn_score": 1, "explore_score": 0, "compete_score": 0.25, "description_lemmatized": "consumer finance protection bureau complaint analysis", "tags_descriptive": ["Classification", "Sentiment Analysis"]}